[
    {
        "url" : "./image/shopList/img%20(93).jpg",
        "p" : "减轻颈部刺痛感 阿兰图案 高领毛衣",
        "new" : "￥ 224",
        "old" : "￥ 448",
        "number" : "月销量 105",
        "id" : "17"
    },
    {
        "url" : "./image/shopList/img%20(265).jpg",
        "p" : "弹力 长毛抓绒 夹克",
        "new" : "￥ 124",
        "old" : "￥ 248",
        "number" : "月销量 182",
        "id" : "18"
    },
    {
        "url" : "./image/shopList/img%20(113).jpg",
        "p" : "含牦牛绒羊毛 款罗纹编织 高圆领毛",
        "new" : "￥ 249",
        "old" : "￥ 498",
        "number" : "月销量 40",
        "id" : "19"
    },
    {
        "url" : "./image/shopList/img (41).jpg",
        "p" : "法国羊毛混 双面大衣",
        "new" : "￥ 499",
        "old" : "￥ 998",
        "number" : "月销量 23",
        "id" : "20"
    },
    {
        "url" : "./image/shopList/img%20(334).jpg",
        "p" : "含牦牛绒羊毛 宽版毛衣",
        "new" : "￥ 249",
        "old" : "￥ 498",
        "number" : "月销量 85",
        "id" : "1"
    },
    {
        "url" : "./image/shopList/img%20(36).jpg",
        "p" : "新疆棉法兰绒 束腰长上衣",
        "new" : "￥ 129",
        "old" : "￥ 248",
        "number" : "月销量 69",
        "id" : "22"
    },
    {
        "url" : "./image/shopList/img%20(137).jpg",
        "p" : "不易沾水 无领大衣",
        "new" : "￥ 598",
        "old" : "",
        "number" : "月销量 8",
        "id" : "23"
    },
    {
        "url" : "./image/shopList/img%20(82).jpg",
        "p" : "减轻颈部刺痛感 宽罗纹 高领毛衣",
        "new" : "￥ 174",
        "old" : "￥ 348",
        "number" : "月销量 22",
        "id" : "24"
    },
    {
        "url" : "./image/shopList/img%20(141).jpg",
        "p" : "不易沾水便携 防风夹克",
        "new" : "￥ 298",
        "old" : "",
        "number" : "月销量 2",
        "id" : "25"
    },
    {
        "url" : "./image/shopList/img%20(101).jpg",
        "p" : "减轻颈部刺痛感 宽罗纹 半高领毛衣",
        "new" : "￥ 174",
        "old" : "￥ 348",
        "number" : "月销量 19",
        "id" : "26"
    },
    {
        "url" : "./image/shopList/img%20(193).jpg",
        "p" : "棉柞蚕丝 平针编织 圆领开衫",
        "new" : "￥ 298",
        "old" : "",
        "number" : "月销量 6",
        "id" : "27"
    },
    {
        "url" : "./image/shopList/img%20(325).jpg",
        "p" : "减轻颈部刺痛感 天竺 半高领毛衣",
        "new" : "￥ 268",
        "old" : "",
        "number" : "月销量 15",
        "id" : "28"
    },
    {
        "url" : "./image/shopList/img%20(177).jpg",
        "p" : "面柞蚕丝 平针编织 高领衫",
        "new" : "￥ 298",
        "old" : "",
        "number" : "月销量 1",
        "id" : "29"
    },
    {
        "url" : "./image/shopList/img%20(185).jpg",
        "p" : "面柞蚕丝 平针编织 圆领衫",
        "new" : "￥ 298",
        "old" : "",
        "number" : "月销量 1",
        "id" : "30"
    },
    {
        "url" : "./image/shopList/img%20(278).jpg",
        "p" : "印度棉 灯芯绒 立领衬衫",
        "new" : "￥ 149",
        "old" : "￥ 298",
        "number" : "月销量 14",
        "id" : "31"
    }
]