[
  {
    "id": 1,
    "type": "superVIP",
    "account": [
      {
        "id": 1,
        "phone": "153 7423 8927",
        "pass": "123456"
      }
    ]
  }
  ,{
    "id": 2,
    "type": "vipUsers",
    "account": [
      {
        "id": 1,
        "phone": "136 7222 4407",
        "pass": "123456"
      },{
        "id": 2,
        "phone": "136 7236 4407",
        "pass": "123456"
      }
    ]
  }
  ,{
    "id": 3,
    "type": "normalUsers",
    "account": [
      {
        "id": 1,
        "phone": "136 7532 4407",
        "pass": "123456"
      },{
        "id": 2,
        "phone": "136 4561 4407",
        "pass": "1234"
      },{
        "id": 3,
        "phone": "136 2135 4407",
        "pass": "7894"
      }
    ]
  }
]
